haarpy/__init__.py
haarpy/_version.py
haarpy/circular_ensembles.py
haarpy/orthogonal.py
haarpy/partition.py
haarpy/permutation.py
haarpy/symmetric.py
haarpy/symplectic.py
haarpy/unitary.py
haarpy/tests/__init__.py
haarpy/tests/test_about.py
haarpy/tests/test_circular_ensembles.py
haarpy/tests/test_orthogonal.py
haarpy/tests/test_partition.py
haarpy/tests/test_permutation.py
haarpy/tests/test_symmetric.py
haarpy/tests/test_symplectic.py
haarpy/tests/test_unitary.py
haarpy-0.0.6.dist-info/licenses/LICENSE
haarpy-0.0.6.dist-info/METADATA
haarpy-0.0.6.dist-info/WHEEL
haarpy-0.0.6.dist-info/top_level.txt
haarpy-0.0.6.dist-info/RECORD
